{
	"display": {
		"icon": {
			"item": "biomesoplenty:flowering_oak_sapling"
		},
		"title": {"translate":"果园"},
		"description": {"color":"green","translate":"找到果园"},
		"frame": "task",
		"announce_to_chat": true
	},
	"parent": "betterbiome:biomesoplenty/biomesoplenty",
	"criteria": {
		"biomesoplenty:orchard": {
			"trigger": "minecraft:location",
			"conditions": {
				"player": {
					"location": {
						"biome": "biomesoplenty:orchard"
					}
				}
			}
		}
	},
	"rewards" :{
		"function" :"betterbiome:biomesoplenty_get"
	}
}